README.txt
setup.py
faresbasiccalculator/__init__.py
faresbasiccalculator.egg-info/PKG-INFO
faresbasiccalculator.egg-info/SOURCES.txt
faresbasiccalculator.egg-info/dependency_links.txt
faresbasiccalculator.egg-info/top_level.txt